lockss/glutinator/__init__.py
lockss/glutinator/__main__.py
lockss/glutinator/app.py
lockss/glutinator/cli.py
lockss/glutinator/csl_data.py
lockss/glutinator/item.py
lockss/glutinator/resources/editorial/assets/css/fontawesome-all.min.css
lockss/glutinator/resources/editorial/assets/css/main.css
lockss/glutinator/resources/editorial/assets/images/licenses/by-nc-nd.png
lockss/glutinator/resources/editorial/assets/images/licenses/by.png
lockss/glutinator/resources/editorial/assets/js/breakpoints.min.js
lockss/glutinator/resources/editorial/assets/js/browser.min.js
lockss/glutinator/resources/editorial/assets/js/jquery.min.js
lockss/glutinator/resources/editorial/assets/js/main.js
lockss/glutinator/resources/editorial/assets/js/util.js
lockss/glutinator/resources/editorial/assets/sass/base/_page.scss
lockss/glutinator/resources/editorial/assets/sass/base/_reset.scss
lockss/glutinator/resources/editorial/assets/sass/base/_typography.scss
lockss/glutinator/resources/editorial/assets/sass/components/_actions.scss
lockss/glutinator/resources/editorial/assets/sass/components/_box.scss
lockss/glutinator/resources/editorial/assets/sass/components/_button.scss
lockss/glutinator/resources/editorial/assets/sass/components/_contact.scss
lockss/glutinator/resources/editorial/assets/sass/components/_features.scss
lockss/glutinator/resources/editorial/assets/sass/components/_form.scss
lockss/glutinator/resources/editorial/assets/sass/components/_icon.scss
lockss/glutinator/resources/editorial/assets/sass/components/_icons.scss
lockss/glutinator/resources/editorial/assets/sass/components/_image.scss
lockss/glutinator/resources/editorial/assets/sass/components/_list.scss
lockss/glutinator/resources/editorial/assets/sass/components/_mini-posts.scss
lockss/glutinator/resources/editorial/assets/sass/components/_pagination.scss
lockss/glutinator/resources/editorial/assets/sass/components/_posts.scss
lockss/glutinator/resources/editorial/assets/sass/components/_row.scss
lockss_glutinator-0.1.0.dev8.dist-info/LICENSE
lockss_glutinator-0.1.0.dev8.dist-info/METADATA
lockss_glutinator-0.1.0.dev8.dist-info/WHEEL
lockss_glutinator-0.1.0.dev8.dist-info/entry_points.txt
lockss_glutinator-0.1.0.dev8.dist-info/RECORD
