Metadata-Version: 2.3
Name: lockss-glutinator
Version: 0.1.0.dev8
Summary: 
License: BSD-3-Clause
Author: Thib Guicherd-Callin
Author-email: thib@cs.stanford.edu
Requires-Python: >=3.9,<4.0
Classifier: License :: OSI Approved :: BSD License
Classifier: Programming Language :: Python :: 3
Classifier: Programming Language :: Python :: 3.9
Classifier: Programming Language :: Python :: 3.10
Classifier: Programming Language :: Python :: 3.11
Classifier: Programming Language :: Python :: 3.12
Classifier: Programming Language :: Python :: 3.13
Requires-Dist: jinja2 (==3.1.5)
Requires-Dist: pydantic (==2.10.6)
Requires-Dist: pyyaml (==6.0.2)
Requires-Dist: rich-argparse (==1.7.0)
Requires-Dist: split-file-reader (==0.1.4)
